caspyr/__init__.py
caspyr/__main__.py
caspyr/_main.py
caspyr/_version.py
caspyr/cuda/__init__.py
caspyr/cuda/_cuda_func.py
caspyr/io/__init__.py
caspyr/io/_h5reader.py
caspyr/multiprocessing/__init__.py
caspyr/multiprocessing/_multiprocessing.py
caspyr/multiprocessing/_promises.py
caspyr/plotting/__init__.py
caspyr/plotting/_errorbar3d.py
caspyr/plotting/_plotting.py
caspyr/plotting/_show.py
caspyr/scripts/__init__.py
caspyr/scripts/duplicate.py
caspyr/scripts/file.py
caspyr/scripts/nvsmi.py
caspyr/scripts/pandoc_filter.py
caspyr/scripts/plot3d.py
caspyr/scripts/pusher.py
caspyr/scripts/remv.py
caspyr/scripts/showslice.py
caspyr/utils/__init__.py
caspyr/utils/_globber.py
caspyr/utils/_logging.py
caspyr/utils/_memoise.py
caspyr/utils/_profile.py
caspyr/utils/_table.py
caspyr/utils/_term.py
caspyr-1.1.1.dist-info/METADATA
caspyr-1.1.1.dist-info/WHEEL
caspyr-1.1.1.dist-info/entry_points.txt
caspyr-1.1.1.dist-info/top_level.txt
caspyr-1.1.1.dist-info/RECORD
